Workbook

Sheet Summary
A1: IT Asset Management — Test Case Suite
A3: Application | B3: IT Transformation Hub (ithub-uat.niytri.com)
A4: Scope | B4: IT Asset Management module + Central Identity (Ashika Portal SSO) & RBAC
A5: Build / Release | B5: Release 2026-10 — contracts/AMC, warranty, depreciation, license compliance, asset dashboard, central identity
A6: Automated run | B6: 2026-10-18 · local UAT replica with mock Ashika Portal (SSO endpoints per Integration Guide v1.1)
A7: Prepared by | B7: NIYTRI Technologies
A10: Module | B10: Sub-module | C10: Total cases | D10: Automated Pass | E10: Automated Fail | F10: Manual (UAT) | G10: UAT Pass | H10: UAT Fail | I10: UAT Pending
A11: IT Asset Management | B11: Asset Registry | C11: =COUNTIFS('Test Cases'!$B$2:$B$106,$A11,'Test Cases'!$C$2:$C$106,$B11) -> 12 | D11: =COUNTIFS('Test Cases'!$B$2:$B$106,$A11,'Test Cases'!$C$2:$C$106,$B11,'Test Cases'!$J$2:$J$106,"Pass") -> 8 | E11: =COUNTIFS('Test Cases'!$B$2:$B$106,$A11,'Test Cases'!$C$2:$C$106,$B11,'Test Cases'!$J$2:$J$106,"Fail") -> 0 | F11: =COUNTIFS('Test Cases'!$B$2:$B$106,$A11,'Test Cases'!$C$2:$C$106,$B11,'Test Cases'!$J$2:$J$106,"Manual (UAT)") -> 4 | G11: =COUNTIFS('Test Cases'!$B$2:$B$106,$A11,'Test Cases'!$C$2:$C$106,$B11,'Test Cases'!$L$2:$L$106,"Pass") -> 0 | H11: =COUNTIFS('Test Cases'!$B$2:$B$106,$A11,'Test Cases'!$C$2:$C$106,$B11,'Test Cases'!$L$2:$L$106,"Fail") -> 0 | I11: =C11-G11-H11 -> 12
A12: IT Asset Management | B12: Asset Register Upload | C12: =COUNTIFS('Test Cases'!$B$2:$B$106,$A12,'Test Cases'!$C$2:$C$106,$B12) -> 3 | D12: =COUNTIFS('Test Cases'!$B$2:$B$106,$A12,'Test Cases'!$C$2:$C$106,$B12,'Test Cases'!$J$2:$J$106,"Pass") -> 2 | E12: =COUNTIFS('Test Cases'!$B$2:$B$106,$A12,'Test Cases'!$C$2:$C$106,$B12,'Test Cases'!$J$2:$J$106,"Fail") -> 0 | F12: =COUNTIFS('Test Cases'!$B$2:$B$106,$A12,'Test Cases'!$C$2:$C$106,$B12,'Test Cases'!$J$2:$J$106,"Manual (UAT)") -> 1 | G12: =COUNTIFS('Test Cases'!$B$2:$B$106,$A12,'Test Cases'!$C$2:$C$106,$B12,'Test Cases'!$L$2:$L$106,"Pass") -> 0 | H12: =COUNTIFS('Test Cases'!$B$2:$B$106,$A12,'Test Cases'!$C$2:$C$106,$B12,'Test Cases'!$L$2:$L$106,"Fail") -> 0 | I12: =C12-G12-H12 -> 3
A13: IT Asset Management | B13: Handovers | C13: =COUNTIFS('Test Cases'!$B$2:$B$106,$A13,'Test Cases'!$C$2:$C$106,$B13) -> 8 | D13: =COUNTIFS('Test Cases'!$B$2:$B$106,$A13,'Test Cases'!$C$2:$C$106,$B13,'Test Cases'!$J$2:$J$106,"Pass") -> 6 | E13: =COUNTIFS('Test Cases'!$B$2:$B$106,$A13,'Test Cases'!$C$2:$C$106,$B13,'Test Cases'!$J$2:$J$106,"Fail") -> 0 | F13: =COUNTIFS('Test Cases'!$B$2:$B$106,$A13,'Test Cases'!$C$2:$C$106,$B13,'Test Cases'!$J$2:$J$106,"Manual (UAT)") -> 2 | G13: =COUNTIFS('Test Cases'!$B$2:$B$106,$A13,'Test Cases'!$C$2:$C$106,$B13,'Test Cases'!$L$2:$L$106,"Pass") -> 0 | H13: =COUNTIFS('Test Cases'!$B$2:$B$106,$A13,'Test Cases'!$C$2:$C$106,$B13,'Test Cases'!$L$2:$L$106,"Fail") -> 0 | I13: =C13-G13-H13 -> 8
A14: IT Asset Management | B14: Lifecycle | C14: =COUNTIFS('Test Cases'!$B$2:$B$106,$A14,'Test Cases'!$C$2:$C$106,$B14) -> 4 | D14: =COUNTIFS('Test Cases'!$B$2:$B$106,$A14,'Test Cases'!$C$2:$C$106,$B14,'Test Cases'!$J$2:$J$106,"Pass") -> 4 | E14: =COUNTIFS('Test Cases'!$B$2:$B$106,$A14,'Test Cases'!$C$2:$C$106,$B14,'Test Cases'!$J$2:$J$106,"Fail") -> 0 | F14: =COUNTIFS('Test Cases'!$B$2:$B$106,$A14,'Test Cases'!$C$2:$C$106,$B14,'Test Cases'!$J$2:$J$106,"Manual (UAT)") -> 0 | G14: =COUNTIFS('Test Cases'!$B$2:$B$106,$A14,'Test Cases'!$C$2:$C$106,$B14,'Test Cases'!$L$2:$L$106,"Pass") -> 0 | H14: =COUNTIFS('Test Cases'!$B$2:$B$106,$A14,'Test Cases'!$C$2:$C$106,$B14,'Test Cases'!$L$2:$L$106,"Fail") -> 0 | I14: =C14-G14-H14 -> 4
A15: IT Asset Management | B15: My Assets | C15: =COUNTIFS('Test Cases'!$B$2:$B$106,$A15,'Test Cases'!$C$2:$C$106,$B15) -> 1 | D15: =COUNTIFS('Test Cases'!$B$2:$B$106,$A15,'Test Cases'!$C$2:$C$106,$B15,'Test Cases'!$J$2:$J$106,"Pass") -> 1 | E15: =COUNTIFS('Test Cases'!$B$2:$B$106,$A15,'Test Cases'!$C$2:$C$106,$B15,'Test Cases'!$J$2:$J$106,"Fail") -> 0 | F15: =COUNTIFS('Test Cases'!$B$2:$B$106,$A15,'Test Cases'!$C$2:$C$106,$B15,'Test Cases'!$J$2:$J$106,"Manual (UAT)") -> 0 | G15: =COUNTIFS('Test Cases'!$B$2:$B$106,$A15,'Test Cases'!$C$2:$C$106,$B15,'Test Cases'!$L$2:$L$106,"Pass") -> 0 | H15: =COUNTIFS('Test Cases'!$B$2:$B$106,$A15,'Test Cases'!$C$2:$C$106,$B15,'Test Cases'!$L$2:$L$106,"Fail") -> 0 | I15: =C15-G15-H15 -> 1
A16: IT Asset Management | B16: Physical Audit | C16: =COUNTIFS('Test Cases'!$B$2:$B$106,$A16,'Test Cases'!$C$2:$C$106,$B16) -> 5 | D16: =COUNTIFS('Test Cases'!$B$2:$B$106,$A16,'Test Cases'!$C$2:$C$106,$B16,'Test Cases'!$J$2:$J$106,"Pass") -> 4 | E16: =COUNTIFS('Test Cases'!$B$2:$B$106,$A16,'Test Cases'!$C$2:$C$106,$B16,'Test Cases'!$J$2:$J$106,"Fail") -> 0 | F16: =COUNTIFS('Test Cases'!$B$2:$B$106,$A16,'Test Cases'!$C$2:$C$106,$B16,'Test Cases'!$J$2:$J$106,"Manual (UAT)") -> 1 | G16: =COUNTIFS('Test Cases'!$B$2:$B$106,$A16,'Test Cases'!$C$2:$C$106,$B16,'Test Cases'!$L$2:$L$106,"Pass") -> 0 | H16: =COUNTIFS('Test Cases'!$B$2:$B$106,$A16,'Test Cases'!$C$2:$C$106,$B16,'Test Cases'!$L$2:$L$106,"Fail") -> 0 | I16: =C16-G16-H16 -> 5
A17: IT Asset Management | B17: Contracts & AMC | C17: =COUNTIFS('Test Cases'!$B$2:$B$106,$A17,'Test Cases'!$C$2:$C$106,$B17) -> 7 | D17: =COUNTIFS('Test Cases'!$B$2:$B$106,$A17,'Test Cases'!$C$2:$C$106,$B17,'Test Cases'!$J$2:$J$106,"Pass") -> 5 | E17: =COUNTIFS('Test Cases'!$B$2:$B$106,$A17,'Test Cases'!$C$2:$C$106,$B17,'Test Cases'!$J$2:$J$106,"Fail") -> 0 | F17: =COUNTIFS('Test Cases'!$B$2:$B$106,$A17,'Test Cases'!$C$2:$C$106,$B17,'Test Cases'!$J$2:$J$106,"Manual (UAT)") -> 2 | G17: =COUNTIFS('Test Cases'!$B$2:$B$106,$A17,'Test Cases'!$C$2:$C$106,$B17,'Test Cases'!$L$2:$L$106,"Pass") -> 0 | H17: =COUNTIFS('Test Cases'!$B$2:$B$106,$A17,'Test Cases'!$C$2:$C$106,$B17,'Test Cases'!$L$2:$L$106,"Fail") -> 0 | I17: =C17-G17-H17 -> 7
A18: IT Asset Management | B18: Depreciation | C18: =COUNTIFS('Test Cases'!$B$2:$B$106,$A18,'Test Cases'!$C$2:$C$106,$B18) -> 9 | D18: =COUNTIFS('Test Cases'!$B$2:$B$106,$A18,'Test Cases'!$C$2:$C$106,$B18,'Test Cases'!$J$2:$J$106,"Pass") -> 7 | E18: =COUNTIFS('Test Cases'!$B$2:$B$106,$A18,'Test Cases'!$C$2:$C$106,$B18,'Test Cases'!$J$2:$J$106,"Fail") -> 0 | F18: =COUNTIFS('Test Cases'!$B$2:$B$106,$A18,'Test Cases'!$C$2:$C$106,$B18,'Test Cases'!$J$2:$J$106,"Manual (UAT)") -> 2 | G18: =COUNTIFS('Test Cases'!$B$2:$B$106,$A18,'Test Cases'!$C$2:$C$106,$B18,'Test Cases'!$L$2:$L$106,"Pass") -> 0 | H18: =COUNTIFS('Test Cases'!$B$2:$B$106,$A18,'Test Cases'!$C$2:$C$106,$B18,'Test Cases'!$L$2:$L$106,"Fail") -> 0 | I18: =C18-G18-H18 -> 9
A19: IT Asset Management | B19: Licenses | C19: =COUNTIFS('Test Cases'!$B$2:$B$106,$A19,'Test Cases'!$C$2:$C$106,$B19) -> 11 | D19: =COUNTIFS('Test Cases'!$B$2:$B$106,$A19,'Test Cases'!$C$2:$C$106,$B19,'Test Cases'!$J$2:$J$106,"Pass") -> 9 | E19: =COUNTIFS('Test Cases'!$B$2:$B$106,$A19,'Test Cases'!$C$2:$C$106,$B19,'Test Cases'!$J$2:$J$106,"Fail") -> 0 | F19: =COUNTIFS('Test Cases'!$B$2:$B$106,$A19,'Test Cases'!$C$2:$C$106,$B19,'Test Cases'!$J$2:$J$106,"Manual (UAT)") -> 2 | G19: =COUNTIFS('Test Cases'!$B$2:$B$106,$A19,'Test Cases'!$C$2:$C$106,$B19,'Test Cases'!$L$2:$L$106,"Pass") -> 0 | H19: =COUNTIFS('Test Cases'!$B$2:$B$106,$A19,'Test Cases'!$C$2:$C$106,$B19,'Test Cases'!$L$2:$L$106,"Fail") -> 0 | I19: =C19-G19-H19 -> 11
A20: IT Asset Management | B20: Vendors | C20: =COUNTIFS('Test Cases'!$B$2:$B$106,$A20,'Test Cases'!$C$2:$C$106,$B20) -> 1 | D20: =COUNTIFS('Test Cases'!$B$2:$B$106,$A20,'Test Cases'!$C$2:$C$106,$B20,'Test Cases'!$J$2:$J$106,"Pass") -> 1 | E20: =COUNTIFS('Test Cases'!$B$2:$B$106,$A20,'Test Cases'!$C$2:$C$106,$B20,'Test Cases'!$J$2:$J$106,"Fail") -> 0 | F20: =COUNTIFS('Test Cases'!$B$2:$B$106,$A20,'Test Cases'!$C$2:$C$106,$B20,'Test Cases'!$J$2:$J$106,"Manual (UAT)") -> 0 | G20: =COUNTIFS('Test Cases'!$B$2:$B$106,$A20,'Test Cases'!$C$2:$C$106,$B20,'Test Cases'!$L$2:$L$106,"Pass") -> 0 | H20: =COUNTIFS('Test Cases'!$B$2:$B$106,$A20,'Test Cases'!$C$2:$C$106,$B20,'Test Cases'!$L$2:$L$106,"Fail") -> 0 | I20: =C20-G20-H20 -> 1
A21: IT Asset Management | B21: Asset Dashboard | C21: =COUNTIFS('Test Cases'!$B$2:$B$106,$A21,'Test Cases'!$C$2:$C$106,$B21) -> 4 | D21: =COUNTIFS('Test Cases'!$B$2:$B$106,$A21,'Test Cases'!$C$2:$C$106,$B21,'Test Cases'!$J$2:$J$106,"Pass") -> 2 | E21: =COUNTIFS('Test Cases'!$B$2:$B$106,$A21,'Test Cases'!$C$2:$C$106,$B21,'Test Cases'!$J$2:$J$106,"Fail") -> 0 | F21: =COUNTIFS('Test Cases'!$B$2:$B$106,$A21,'Test Cases'!$C$2:$C$106,$B21,'Test Cases'!$J$2:$J$106,"Manual (UAT)") -> 2 | G21: =COUNTIFS('Test Cases'!$B$2:$B$106,$A21,'Test Cases'!$C$2:$C$106,$B21,'Test Cases'!$L$2:$L$106,"Pass") -> 0 | H21: =COUNTIFS('Test Cases'!$B$2:$B$106,$A21,'Test Cases'!$C$2:$C$106,$B21,'Test Cases'!$L$2:$L$106,"Fail") -> 0 | I21: =C21-G21-H21 -> 4
A22: IT Asset Management | B22: QR Stickers | C22: =COUNTIFS('Test Cases'!$B$2:$B$106,$A22,'Test Cases'!$C$2:$C$106,$B22) -> 3 | D22: =COUNTIFS('Test Cases'!$B$2:$B$106,$A22,'Test Cases'!$C$2:$C$106,$B22,'Test Cases'!$J$2:$J$106,"Pass") -> 0 | E22: =COUNTIFS('Test Cases'!$B$2:$B$106,$A22,'Test Cases'!$C$2:$C$106,$B22,'Test Cases'!$J$2:$J$106,"Fail") -> 0 | F22: =COUNTIFS('Test Cases'!$B$2:$B$106,$A22,'Test Cases'!$C$2:$C$106,$B22,'Test Cases'!$J$2:$J$106,"Manual (UAT)") -> 3 | G22: =COUNTIFS('Test Cases'!$B$2:$B$106,$A22,'Test Cases'!$C$2:$C$106,$B22,'Test Cases'!$L$2:$L$106,"Pass") -> 0 | H22: =COUNTIFS('Test Cases'!$B$2:$B$106,$A22,'Test Cases'!$C$2:$C$106,$B22,'Test Cases'!$L$2:$L$106,"Fail") -> 0 | I22: =C22-G22-H22 -> 3
... A27: IT Asset Management | B27: Performance | C27: =COUNTIFS('Test Cases'!$B$2:$B$106,$A27,'Test Cases'!$C$2:$C$106,$B27) -> 1 | D27: =COUNTIFS('Test Cases'!$B$2:$B$106,$A27,'Test Cases'!$C$2:$C$106,$B27,'Test Cases'!$J$2:$J$106,"Pass") -> 0 | E27: =COUNTIFS('Test Cases'!$B$2:$B$106,$A27,'Test Cases'!$C$2:$C$106,$B27,'Test Cases'!$J$2:$J$106,"Fail") -> 0 | F27: =COUNTIFS('Test Cases'!$B$2:$B$106,$A27,'Test Cases'!$C$2:$C$106,$B27,'Test Cases'!$J$2:$J$106,"Manual (UAT)") -> 1 | G27: =COUNTIFS('Test Cases'!$B$2:$B$106,$A27,'Test Cases'!$C$2:$C$106,$B27,'Test Cases'!$L$2:$L$106,"Pass") -> 0 | H27: =COUNTIFS('Test Cases'!$B$2:$B$106,$A27,'Test Cases'!$C$2:$C$106,$B27,'Test Cases'!$L$2:$L$106,"Fail") -> 0 | I27: =C27-G27-H27 -> 1
A28: IT Asset Management — subtotal | C28: =SUM(C11:C27) -> 74 | D28: =SUM(D11:D27) -> 49 | E28: =SUM(E11:E27) -> 0 | F28: =SUM(F11:F27) -> 25 | G28: =SUM(G11:G27) -> 0 | H28: =SUM(H11:H27) -> 0 | I28: =SUM(I11:I27) -> 74
A29: Identity & Access Management | B29: Central Identity (Ashika Portal SSO) | C29: =COUNTIFS('Test Cases'!$B$2:$B$106,$A29,'Test Cases'!$C$2:$C$106,$B29) -> 18 | D29: =COUNTIFS('Test Cases'!$B$2:$B$106,$A29,'Test Cases'!$C$2:$C$106,$B29,'Test Cases'!$J$2:$J$106,"Pass") -> 14 | E29: =COUNTIFS('Test Cases'!$B$2:$B$106,$A29,'Test Cases'!$C$2:$C$106,$B29,'Test Cases'!$J$2:$J$106,"Fail") -> 0 | F29: =COUNTIFS('Test Cases'!$B$2:$B$106,$A29,'Test Cases'!$C$2:$C$106,$B29,'Test Cases'!$J$2:$J$106,"Manual (UAT)") -> 4 | G29: =COUNTIFS('Test Cases'!$B$2:$B$106,$A29,'Test Cases'!$C$2:$C$106,$B29,'Test Cases'!$L$2:$L$106,"Pass") -> 0 | H29: =COUNTIFS('Test Cases'!$B$2:$B$106,$A29,'Test Cases'!$C$2:$C$106,$B29,'Test Cases'!$L$2:$L$106,"Fail") -> 0 | I29: =C29-G29-H29 -> 18
A30: Identity & Access Management | B30: Role-based Access (RBAC) | C30: =COUNTIFS('Test Cases'!$B$2:$B$106,$A30,'Test Cases'!$C$2:$C$106,$B30) -> 10 | D30: =COUNTIFS('Test Cases'!$B$2:$B$106,$A30,'Test Cases'!$C$2:$C$106,$B30,'Test Cases'!$J$2:$J$106,"Pass") -> 10 | E30: =COUNTIFS('Test Cases'!$B$2:$B$106,$A30,'Test Cases'!$C$2:$C$106,$B30,'Test Cases'!$J$2:$J$106,"Fail") -> 0 | F30: =COUNTIFS('Test Cases'!$B$2:$B$106,$A30,'Test Cases'!$C$2:$C$106,$B30,'Test Cases'!$J$2:$J$106,"Manual (UAT)") -> 0 | G30: =COUNTIFS('Test Cases'!$B$2:$B$106,$A30,'Test Cases'!$C$2:$C$106,$B30,'Test Cases'!$L$2:$L$106,"Pass") -> 0 | H30: =COUNTIFS('Test Cases'!$B$2:$B$106,$A30,'Test Cases'!$C$2:$C$106,$B30,'Test Cases'!$L$2:$L$106,"Fail") -> 0 | I30: =C30-G30-H30 -> 10
A31: Identity & Access Management | B31: API Security | C31: =COUNTIFS('Test Cases'!$B$2:$B$106,$A31,'Test Cases'!$C$2:$C$106,$B31) -> 2 | D31: =COUNTIFS('Test Cases'!$B$2:$B$106,$A31,'Test Cases'!$C$2:$C$106,$B31,'Test Cases'!$J$2:$J$106,"Pass") -> 2 | E31: =COUNTIFS('Test Cases'!$B$2:$B$106,$A31,'Test Cases'!$C$2:$C$106,$B31,'Test Cases'!$J$2:$J$106,"Fail") -> 0 | F31: =COUNTIFS('Test Cases'!$B$2:$B$106,$A31,'Test Cases'!$C$2:$C$106,$B31,'Test Cases'!$J$2:$J$106,"Manual (UAT)") -> 0 | G31: =COUNTIFS('Test Cases'!$B$2:$B$106,$A31,'Test Cases'!$C$2:$C$106,$B31,'Test Cases'!$L$2:$L$106,"Pass") -> 0 | H31: =COUNTIFS('Test Cases'!$B$2:$B$106,$A31,'Test Cases'!$C$2:$C$106,$B31,'Test Cases'!$L$2:$L$106,"Fail") -> 0 | I31: =C31-G31-H31 -> 2
A32: Identity & Access Management | B32: Roles & Permissions | C32: =COUNTIFS('Test Cases'!$B$2:$B$106,$A32,'Test Cases'!$C$2:$C$106,$B32) -> 1 | D32: =COUNTIFS('Test Cases'!$B$2:$B$106,$A32,'Test Cases'!$C$2:$C$106,$B32,'Test Cases'!$J$2:$J$106,"Pass") -> 0 | E32: =COUNTIFS('Test Cases'!$B$2:$B$106,$A32,'Test Cases'!$C$2:$C$106,$B32,'Test Cases'!$J$2:$J$106,"Fail") -> 0 | F32: =COUNTIFS('Test Cases'!$B$2:$B$106,$A32,'Test Cases'!$C$2:$C$106,$B32,'Test Cases'!$J$2:$J$106,"Manual (UAT)") -> 1 | G32: =COUNTIFS('Test Cases'!$B$2:$B$106,$A32,'Test Cases'!$C$2:$C$106,$B32,'Test Cases'!$L$2:$L$106,"Pass") -> 0 | H32: =COUNTIFS('Test Cases'!$B$2:$B$106,$A32,'Test Cases'!$C$2:$C$106,$B32,'Test Cases'!$L$2:$L$106,"Fail") -> 0 | I32: =C32-G32-H32 -> 1
A33: Identity & Access Management — subtotal | C33: =SUM(C29:C32) -> 31 | D33: =SUM(D29:D32) -> 26 | E33: =SUM(E29:E32) -> 0 | F33: =SUM(F29:F32) -> 5 | G33: =SUM(G29:G32) -> 0 | H33: =SUM(H29:H32) -> 0 | I33: =SUM(I29:I32) -> 31
A34: Grand total | C34: =C11+C12+C13+C14+C15+C16+C17+C18+C19+C20+C21+C22+C23+C24+C25+C26+C27+C29+C30+C31+C32 -> 105 | D34: =D11+D12+D13+D14+D15+D16+D17+D18+D19+D20+D21+D22+D23+D24+D25+D26+D27+D29+D30+D31+D32 -> 75 | E34: =E11+E12+E13+E14+E15+E16+E17+E18+E19+E20+E21+E22+E23+E24+E25+E26+E27+E29+E30+E31+E32 -> 0 | F34: =F11+F12+F13+F14+F15+F16+F17+F18+F19+F20+F21+F22+F23+F24+F25+F26+F27+F29+F30+F31+F32 -> 30 | G34: =G11+G12+G13+G14+G15+G16+G17+G18+G19+G20+G21+G22+G23+G24+G25+G26+G27+G29+G30+G31+G32 -> 0 | H34: =H11+H12+H13+H14+H15+H16+H17+H18+H19+H20+H21+H22+H23+H24+H25+H26+H27+H29+H30+H31+H32 -> 0 | I34: =I11+I12+I13+I14+I15+I16+I17+I18+I19+I20+I21+I22+I23+I24+I25+I26+I27+I29+I30+I31+I32 -> 105
A36: Automated pass rate | B36: =IFERROR(D34/(D34+E34),0) -> 1
A37: UAT pass rate (of executed) | B37: =IFERROR(G34/(G34+H34),0) -> 0
A39: How to use
A40: Yellow cells on 'Test Cases' (UAT Result, Tester, Date, Remarks) are for the client's UAT team — pick Pass / Fail / Blocked / Not Run.
A41: Columns J–K show the automated run done before delivery (API + browser). 'Manual (UAT)' rows are UI checks to execute by hand.
A42: This Summary recalculates automatically from the Test Cases sheet.
A43: Example: UAT Result = Pass, UAT Tester = 'IT Asset team', UAT Date = 2026-10-20, Remarks = 'OK on Chrome / Android'.
A44: Central Identity cases need the Portal admin to register IT Hub first — values on the 'Portal Setup & Page Keys' sheet.

Sheet Test Cases
A1: Test ID | B1: Module | C1: Sub-module | D1: Test Scenario | E1: Pre-conditions | F1: Test Steps (in the application) | G1: Expected Result | H1: Priority | I1: Type | J1: Automated Run (API / Browser) | K1: Automated Run — Actual | L1: UAT Result | M1: UAT Tester | N1: UAT Date | O1: Defect / Remarks
A2: AST-01 | B2: IT Asset Management | C2: Asset Registry | D2: Register a new asset with an automatic tag | E2: Signed in as an IT administrator (or a role with edit on this module). | F2: Asset Registry › Add Asset: choose type Laptop (tag auto-fills), fill name, serial, vendor, location › Create › confirm. [API check: POST /api/assets with type Laptop, serial, vendor] | G2: HTTP 201; tag LAP-####; trail entry "Registered" | H2: High | I2: Positive | J2: Pass | K2: As expected
A3: AST-02 | B3: IT Asset Management | C3: Asset Registry | D3: Duplicate serial number for same type is rejected | E3: Signed in as an IT administrator (or a role with edit on this module). | F3: Add Asset again with the same type and serial number. [API check: POST /api/assets with an existing serial] | G3: HTTP 400 "already exists" | H3: High | I3: Negative | J3: Pass | K3: As expected
A4: AST-03 | B4: IT Asset Management | C4: Asset Registry | D4: New asset cannot start as Allocated | E4: Signed in as an IT administrator (or a role with edit on this module). | F4: (API rule) New assets can be In Stock / In Use / Under Maintenance / Retired only — status list in Add Asset. [API check: POST /api/assets with status Allocated] | G4: HTTP 400 — use Issue instead | H4: High | I4: Negative | J4: Pass | K4: As expected
A5: AST-04 | B5: IT Asset Management | C5: Asset Registry | D5: Edit requires a reason comment | E5: Signed in as an IT administrator (or a role with edit on this module). | F5: Edit the asset, change Location, leave the comment empty, Save. [API check: PATCH /api/assets/:id without comment] | G5: HTTP 400 asking for a comment | H5: High | I5: Negative | J5: Pass | K5: As expected
A6: AST-05 | B6: IT Asset Management | C6: Asset Registry | D6: Edit with comment records a field-level change trail | E6: Signed in as an IT administrator (or a role with edit on this module). | F6: Edit again with a comment, Save; open the asset › History & comments. [API check: PATCH location + comment] | G6: HTTP 200; trail "Updated" with Location from→to and the comment | H6: High | I6: Positive | J6: Pass | K6: As expected
A7: AST-06 | B7: IT Asset Management | C7: Asset Registry | D7: Status cannot be changed through edit | E7: Signed in as an IT administrator (or a role with edit on this module). | F7: Edit form: status is not editable — use lifecycle buttons. [API check: PATCH status=Retired with comment] | G7: Status unchanged (lifecycle actions only) | H7: High | I7: Negative | J7: Pass | K7: As expected
A8: AST-07 | B8: IT Asset Management | C8: Asset Registry | D8: Comment on an asset | E8: Signed in as an IT administrator (or a role with edit on this module). | F8: Asset › History & comments › add a comment. [API check: POST /api/asset-comments/:id] | G8: HTTP 200/201 and visible in trail | H8: High | I8: Positive | J8: Pass | K8: As expected
A9: AST-08 | B9: IT Asset Management | C9: Asset Register Upload | D9: Upload validation rejects bad rows and saves nothing | E9: Signed in as an IT administrator (or a role with edit on this module). | F9: Upload Register with a file containing an invalid type, a bad date and a missing vendor. [API check: POST /api/assets/import (dry run) with invalid type, bad date, missing vendor] | G9: errors listed per row/column; inserted=0 | H9: High | I9: Negative | J9: Pass | K9: As expected
A10: AST-09 | B10: IT Asset Management | C10: Asset Register Upload | D10: Valid upload imports, auto-tags and creates vendors | E10: Signed in as an IT administrator (or a role with edit on this module). | F10: Upload Register with 2 valid rows (one Allocated with Assigned To). [API check: POST /api/assets/import with 2 valid rows (dryRun false)] | G10: inserted=2; tags generated | H10: High | I10: Positive | J10: Pass | K10: As expected
A11: AST-10 | B11: IT Asset Management | C11: Asset Registry | D11: Sample template rows are refused | E11: Signed in as an IT administrator (or a role with edit on this module). | F11: Upload the template without deleting the SAMPLE rows. [API check: Import a row with tag SAMPLE-001] | G11: Row error "Sample row from the template" | H11: High | I11: Negative | J11: Pass | K11: As expected
A12: LC-01 | B12: IT Asset Management | C12: Handovers | D12: Issue an asset to an employee | E12: Signed in as an IT administrator (or a role with edit on this module). | F12: Handovers › Issue assets: pick an In Stock asset, employee details, Permanent, Good › Issue; print handover note. [API check: POST /api/assets/:id/issue (Permanent, condition Good)] | G12: Status Allocated; handover HO-YYYY-##### created, acknowledgement Pending | H12: High | I12: Positive | J12: Pass | K12: As expected
A13: LC-02 | B13: IT Asset Management | C13: Handovers | D13: Temporary issue requires an expected return date | E13: Signed in as an IT administrator (or a role with edit on this module). | F13: Issue as Temporary / Loaner without an expected return date. [API check: Issue with allocationType Temporary and no return date] | G13: HTTP 400 | H13: High | I13: Negative | J13: Pass | K13: As expected
... A76: RBAC-11 | B76: Identity & Access Management | C76: Central Identity (Ashika Portal SSO) | D76: Login page shows Ashika Portal sign-in (browser) | E76: Central Identity enabled; Portal roles configured. | F76: Open /login with Central Identity enabled. | G76: 'Sign in with Ashika Portal' button; password form hidden behind 'Administrator sign-in (break-glass)'. | H76: High | I76: Positive | J76: Pass | K76: As expected (screenshot verified).
A77: UI-01 | B77: IT Asset Management | C77: QR Stickers | D77: Print QR stickers (3 formats) | E77: Signed in with the right role; sample data loaded. | F77: Asset Registry › QR Stickers › choose 50×25 mm, A4 24-up, 85×54 mm › Print. | G77: Stickers show logo, tag, name, serial and a scannable QR; layout fits the label size. | H77: High | I77: Functional | J77: Manual (UAT)
A78: UI-02 | B78: IT Asset Management | C78: QR Stickers | D78: Scan sticker with phone camera (not signed in) | E78: Signed in with the right role; sample data loaded. | F78: Scan a sticker with the phone camera app. | G78: Opens IT Hub login; after sign-in lands on that asset's page. | H78: High | I78: Functional | J78: Manual (UAT)
A79: UI-03 | B79: IT Asset Management | C79: QR Stickers | D79: In-app scanner | E79: Signed in with the right role; sample data loaded. | F79: Open /asset-scan on a phone › allow camera › scan a sticker. | G79: Asset details open; repeat scans within 20 s are ignored in audits. | H79: High | I79: Functional | J79: Manual (UAT)
A80: UI-04 | B80: IT Asset Management | C80: Asset Registry | D80: Search, filters and pagination | E80: Signed in with the right role; sample data loaded. | F80: Search by tag/serial/user; filter type, status, department; page through. | G80: Results update instantly; counts correct. | H80: Medium | I80: Functional | J80: Manual (UAT)
A81: UI-05 | B81: IT Asset Management | C81: Asset Registry | D81: Export CSV | E81: Signed in with the right role; sample data loaded. | F81: Asset Registry › Export CSV. | G81: CSV opens in Excel with all listed assets. | H81: Medium | I81: Functional | J81: Manual (UAT)
A82: UI-06 | B82: IT Asset Management | C82: Asset Register Upload | D82: Download template | E82: Signed in with the right role; sample data loaded. | F82: Upload Register › Template. | G82: Workbook with columns, 3 sample rows, Instructions and Allowed Values sheets. | H82: Medium | I82: Functional | J82: Manual (UAT)
A83: UI-07 | B83: IT Asset Management | C83: Asset Registry | D83: In-app confirmations | E83: Signed in with the right role; sample data loaded. | F83: Create, edit, delete, issue, return, renew, revoke. | G83: Every action shows an in-app confirmation box (never a browser pop-up). | H83: High | I83: Usability | J83: Manual (UAT)
A84: UI-08 | B84: IT Asset Management | C84: Asset Registry | D84: Clear All Data (admin only) | E84: Signed in with the right role; sample data loaded. | F84: As full admin: Asset Registry › Clear All Data › type the confirmation text. | G84: All asset data cleared after typed confirmation; non-admins never see the button. | H84: High | I84: Security | J84: Manual (UAT)
A85: UI-09 | B85: IT Asset Management | C85: Handovers | D85: Handover note print | E85: Signed in with the right role; sample data loaded. | F85: Handovers › print icon on a handover. | G85: Printable note with handover no., asset, accessories, signatures. | H85: Medium | I85: Functional | J85: Manual (UAT)
A86: UI-10 | B86: IT Asset Management | C86: Handovers | D86: Overdue temporary returns | E86: Signed in with the right role; sample data loaded. | F86: Issue as Temporary with a past return date › Handovers › Overdue returns tab. | G86: Listed in red; counted on the dashboard. | H86: Medium | I86: Functional | J86: Manual (UAT)
A87: UI-11 | B87: IT Asset Management | C87: Employee Assets | D87: Employee view | E87: Signed in with the right role; sample data loaded. | F87: Employee Assets › select an employee. | G87: All assets held, with handover numbers and acknowledgement status. | H87: Medium | I87: Functional | J87: Manual (UAT)
A88: UI-12 | B88: IT Asset Management | C88: History | D88: Asset history trail | E88: Signed in with the right role; sample data loaded. | F88: Open any asset › History & comments. | G88: Every change shows who, when, what changed (from → to) and the comment. | H88: High | I88: Audit | J88: Manual (UAT)
... A106: UI-30 | B106: IT Asset Management | C106: Performance | D106: Large register | E106: Signed in with the right role; sample data loaded. | F106: Upload 2,000+ assets; open Registry, Dashboard, Depreciation. | G106: Pages load within 3 seconds. | H106: Medium | I106: Performance | J106: Manual (UAT)

Sheet Portal Setup & Page Keys
A1: Ashika Portal — IT Hub registration (sso_apps)
A3: client_id | B3: it-hub
A4: redirect_uris | B4: https://ithub-uat.niytri.com/api/auth/central/callback
A5: client_secret | B5: Generated by the Portal admin; given to the IT Hub server admin privately (never by email/chat)
A6: allowed_roles | B6: Optional — leave blank and control access through role_applications
A7: application | B7: Tag IT Hub roles to the 'IT Hub' application (role_applications)
A10: Page keys used by IT Hub (put these in the Portal role's pages / access)
A11: Page key | B11: IT Hub screen | C11: 'view' allows | D11: 'edit' allows
A12: assets | B12: IT Assets › Asset Dashboard | C12: Dashboard | D12: —
A13: asset_registry | B13: Asset Registry, QR stickers, asset history | C13: View assets, coverage, history | D13: Add / edit / upload / lifecycle (maintenance, retire, dispose), finance upload, comments
A14: asset_allocations | B14: Handovers, Employee Assets | C14: View handovers | D14: Issue, bulk issue, return, record acknowledgement
A15: asset_contracts | B15: Contracts, AMC & Warranty | C15: View contracts and warranty coverage | D15: Create / edit / renew / delete contracts, add or remove covered assets
A16: asset_depreciation | B16: Depreciation | C16: View register and schedules | D16: Change depreciation rules
A17: asset_licenses | B17: Software Licenses & Compliance | C17: View licenses and compliance | D17: Add / edit licenses, assign and revoke seats
A18: asset_vendors | B18: Vendors | C18: View vendors | D18: Add / edit / delete vendors
A19: asset_audits | B19: Physical Audit | C19: View audits and reports | D19: Plan, start, scan, complete, cancel audits
A20: pages: ["*"] | B20: Full access | C20: Everything | D20: Everything incl. Admin, Clear All Data
A22: Suggested Portal roles for IT Hub
A23: Role | B23: pages | C23: access | D23: Use
A24: IT Hub Admin | B24: ["*"] | C24: — | D24: IT head / application admin
A25: IT Asset Manager | B25: ["assets","asset_registry","asset_allocations","asset_contracts","asset_licenses","asset_vendors","asset_audits","asset_depreciation"] | C25: all "edit" except asset_depreciation "view" | D25: Runs the asset desk
A26: Asset Auditor | B26: ["assets","asset_registry","asset_audits"] | C26: asset_audits "edit"; others "view" | D26: Physical verification team
A27: Finance (Assets) | B27: ["assets","asset_registry","asset_depreciation","asset_contracts"] | C27: asset_depreciation "edit"; others "view" | D27: Fixed-asset register, AMC spend
A28: Asset Viewer | B28: ["assets","asset_registry"] | C28: "view" | D28: Management / auditors (read-only)
A30: Every employee can always open My Assets and acknowledge their own handovers; no page key needed.
